[
  {
    "id": "ciencias-01",
    "pregunta": "En un experimento controlado, ¿qué variable se mantiene constante al caso 1?",
    "a": "Variable dependiente",
    "b": "Variable independiente",
    "c": "Variable de control",
    "d": "Error de medición",
    "correcta": "c",
    "OA": "Biología/Química/Física — habilidades científicas",
    "PAES": "Ciencias"
  },
  {
    "id": "ciencias-02",
    "pregunta": "En un experimento controlado, ¿qué variable se mantiene constante al caso 2?",
    "a": "Variable dependiente",
    "b": "Variable independiente",
    "c": "Variable de control",
    "d": "Error de medición",
    "correcta": "c",
    "OA": "Biología/Química/Física — habilidades científicas",
    "PAES": "Ciencias"
  },
  {
    "id": "ciencias-03",
    "pregunta": "En un experimento controlado, ¿qué variable se mantiene constante al caso 3?",
    "a": "Variable dependiente",
    "b": "Variable independiente",
    "c": "Variable de control",
    "d": "Error de medición",
    "correcta": "c",
    "OA": "Biología/Química/Física — habilidades científicas",
    "PAES": "Ciencias"
  },
  {
    "id": "ciencias-04",
    "pregunta": "En un experimento controlado, ¿qué variable se mantiene constante al caso 4?",
    "a": "Variable dependiente",
    "b": "Variable independiente",
    "c": "Variable de control",
    "d": "Error de medición",
    "correcta": "c",
    "OA": "Biología/Química/Física — habilidades científicas",
    "PAES": "Ciencias"
  },
  {
    "id": "ciencias-05",
    "pregunta": "En un experimento controlado, ¿qué variable se mantiene constante al caso 5?",
    "a": "Variable dependiente",
    "b": "Variable independiente",
    "c": "Variable de control",
    "d": "Error de medición",
    "correcta": "c",
    "OA": "Biología/Química/Física — habilidades científicas",
    "PAES": "Ciencias"
  },
  {
    "id": "ciencias-06",
    "pregunta": "En un experimento controlado, ¿qué variable se mantiene constante al caso 6?",
    "a": "Variable dependiente",
    "b": "Variable independiente",
    "c": "Variable de control",
    "d": "Error de medición",
    "correcta": "c",
    "OA": "Biología/Química/Física — habilidades científicas",
    "PAES": "Ciencias"
  },
  {
    "id": "ciencias-07",
    "pregunta": "En un experimento controlado, ¿qué variable se mantiene constante al caso 7?",
    "a": "Variable dependiente",
    "b": "Variable independiente",
    "c": "Variable de control",
    "d": "Error de medición",
    "correcta": "c",
    "OA": "Biología/Química/Física — habilidades científicas",
    "PAES": "Ciencias"
  },
  {
    "id": "ciencias-08",
    "pregunta": "En un experimento controlado, ¿qué variable se mantiene constante al caso 8?",
    "a": "Variable dependiente",
    "b": "Variable independiente",
    "c": "Variable de control",
    "d": "Error de medición",
    "correcta": "c",
    "OA": "Biología/Química/Física — habilidades científicas",
    "PAES": "Ciencias"
  },
  {
    "id": "ciencias-09",
    "pregunta": "En un experimento controlado, ¿qué variable se mantiene constante al caso 9?",
    "a": "Variable dependiente",
    "b": "Variable independiente",
    "c": "Variable de control",
    "d": "Error de medición",
    "correcta": "c",
    "OA": "Biología/Química/Física — habilidades científicas",
    "PAES": "Ciencias"
  },
  {
    "id": "ciencias-10",
    "pregunta": "En un experimento controlado, ¿qué variable se mantiene constante al caso 10?",
    "a": "Variable dependiente",
    "b": "Variable independiente",
    "c": "Variable de control",
    "d": "Error de medición",
    "correcta": "c",
    "OA": "Biología/Química/Física — habilidades científicas",
    "PAES": "Ciencias"
  }
]